TOPSIS_INAYAT_102183050/mytopsis.py
TOPSIS_INAYAT_102183050-0.1.dist-info/LICENCE.txt
TOPSIS_INAYAT_102183050-0.1.dist-info/METADATA
TOPSIS_INAYAT_102183050-0.1.dist-info/WHEEL
TOPSIS_INAYAT_102183050-0.1.dist-info/entry_points.txt
TOPSIS_INAYAT_102183050-0.1.dist-info/top_level.txt
TOPSIS_INAYAT_102183050-0.1.dist-info/RECORD
