Metadata-Version: 2.1
Name: TOPSIS-INAYAT-102183050
Version: 0.1
Summary: A package -> Calculates Topsis Score and Rank them accordingly
Home-page: https://github.com/inayat0203/TOPSIS_INAYAT_102183050
Author: Inayat
Author-email: inayat0203@gmail.com
License: MIT
Classifier: Programming Language :: Python :: 3
Classifier: License :: OSI Approved :: MIT License
Classifier: Operating System :: OS Independent
License-File: LICENCE.txt
Requires-Dist: pandas
